automsr/__init__.py
automsr/browser/__init__.py
automsr/browser/browser.py
automsr/browser/profile.py
automsr/cli.py
automsr/config.py
automsr/datatypes/__init__.py
automsr/datatypes/dashboard.py
automsr/datatypes/execution.py
automsr/executor.py
automsr/init.py
automsr/mail.py
automsr/search.py
automsr-9.7.0.dist-info/LICENSE
automsr-9.7.0.dist-info/METADATA
automsr-9.7.0.dist-info/WHEEL
automsr-9.7.0.dist-info/entry_points.txt
automsr-9.7.0.dist-info/RECORD
