Metadata-Version: 2.1
Name: automsr
Version: 9.7.0
Summary: Automate Rewards points collection
Home-page: https://github.com/Crissal1995/automsr
License: MIT
Author: Cristiano Salerno
Author-email: cristianosalerno1@gmail.com
Requires-Python: >=3.8,<4.0
Classifier: License :: OSI Approved :: MIT License
Classifier: Programming Language :: Python :: 3
Classifier: Programming Language :: Python :: 3.8
Classifier: Programming Language :: Python :: 3.9
Classifier: Programming Language :: Python :: 3.10
Classifier: Programming Language :: Python :: 3.11
Requires-Dist: email-validator (>=2.0.0.post2,<3.0.0)
Requires-Dist: faker (>=19.3.1,<20.0.0)
Requires-Dist: markdown (>=3.4.4,<4.0.0)
Requires-Dist: pydantic (>=2.1.1,<3.0.0)
Requires-Dist: pyyaml (>=6.0.1,<7.0.0)
Requires-Dist: questionary (>=2.0.1,<3.0.0)
Requires-Dist: selenium (>=4.11.2,<5.0.0)
Requires-Dist: tqdm (>=4.65.0,<5.0.0)
Requires-Dist: types-pyyaml (>=6.0.12.11,<7.0.0.0)
Requires-Dist: types-tqdm (>=4.65.0.2,<5.0.0.0)
Project-URL: Repository, https://github.com/Crissal1995/automsr
